httpout/request.py
httpout/__main__.py
httpout/__init__.py
httpout/exceptions.py
httpout/httpout.py
httpout/response.py
httpout/utils/__init__.py
httpout/utils/modules.cpython-37m-x86_64-linux-gnu.so
httpout/utils/modules.py
httpout/utils/modules.pyx
httpout-0.1.1.dist-info/top_level.txt
httpout-0.1.1.dist-info/RECORD
httpout-0.1.1.dist-info/METADATA
httpout-0.1.1.dist-info/WHEEL
httpout-0.1.1.dist-info/LICENSE
