Metadata-Version: 2.1
Name: httpout
Version: 0.1.1
Summary: httpout is a runtime environment for Python files. It allows you to execute your Python scripts from a web URL, the print() output goes to your browser.
Author-email: nggit <contact@anggit.com>
License: MIT License
Project-URL: Homepage, https://github.com/nggit/httpout
Project-URL: Source, https://github.com/nggit/httpout
Project-URL: Funding, https://github.com/sponsors/nggit
Classifier: Development Status :: 4 - Beta
Classifier: Intended Audience :: Developers
Classifier: License :: OSI Approved :: MIT License
Classifier: Operating System :: OS Independent
Classifier: Topic :: Internet :: WWW/HTTP :: HTTP Servers
Classifier: Topic :: Software Development :: Libraries :: Application Frameworks
Requires-Python: >=3.7
License-File: LICENSE
Requires-Dist: tremolo >=0.2.0
